FIR_filter.sv
module FIR_filter #(
    parameter int taps        = 32,
    parameter int num_bits    = 8,
    parameter int input_size  = 8,
    parameter int output_size = (2 * num_bits) + 1
)(
    input  logic                      clock,
    input  logic                      reset,
    input  logic [input_size-1:0]     Data_In,
    output logic [output_size-1:0]    Data_Out
);

    // -----------------------------
    // FILTER COEFFICIENTS
    // -----------------------------
    localparam logic [num_bits-1:0] coeffs [0:taps-1] = '{
        8'b0000_0011, 8'b0000_0010, 8'b0000_0001, 8'b0000_0000,
        8'b0000_0000, 8'b0000_0000, 8'b0000_0000, 8'b0000_0000,
        8'b0000_0000, 8'b0000_0000, 8'b0000_0100, 8'b0000_1100,
        8'b0001_0101, 8'b0001_1110, 8'b0010_0101, 8'b0010_1001,
        8'b0010_1001, 8'b0010_0101, 8'b0001_1110, 8'b0001_0101,
        8'b0000_1100, 8'b0000_0100, 8'b0000_0000, 8'b0000_0000,
        8'b0000_0000, 8'b0000_0000, 8'b0000_0000, 8'b0000_0000,
        8'b0000_0000, 8'b0000_0001, 8'b0000_0010, 8'b0000_0011
    };

    // -----------------------------
    // Delay line register
    // -----------------------------
    logic [input_size-1:0] FIR[taps-1:0];

    // -----------------------------
    // Output Accumulation
    // -----------------------------
    logic [output_size-1:0] acc;
    integer j;

    always_comb begin
        acc = 0;
        for (j = 0; j < taps; j++) begin
            acc += coeffs[j] * FIR[j];
        end
    end

    assign Data_Out = acc;

    // -----------------------------
    // Shift Register Logic
    // -----------------------------
    integer i;
    always_ff @(posedge clock or posedge reset) begin
        if (reset) begin
            for (i = 0; i < taps; i++) begin
                FIR[i] <= 0;
            end
        end else begin
            for (i = taps-1; i > 0; i--) begin
                FIR[i] <= FIR[i-1];
            end
            FIR[0] <= Data_In;
        end
    end

endmodule

waveform_for_high_freq.vcd
$version Generated by VerilatedVcd $end
$timescale 1ps $end
 $scope module TOP $end
  $var wire 1 E clock $end
  $var wire 1 F reset $end
  $var wire 8 G Data_In [7:0] $end
  $var wire 17 H Data_Out [16:0] $end
  $scope module FIR_filter $end
   $var wire 32 I taps [31:0] $end
   $var wire 32 J num_bits [31:0] $end
   $var wire 32 J input_size [31:0] $end
   $var wire 32 K output_size [31:0] $end
   $var wire 1 E clock $end
   $var wire 1 F reset $end
   $var wire 8 G Data_In [7:0] $end
   $var wire 17 H Data_Out [16:0] $end
   $var wire 8 L coeffs[0] [7:0] $end
   $var wire 8 M coeffs[1] [7:0] $end
   $var wire 8 N coeffs[2] [7:0] $end
   $var wire 8 O coeffs[3] [7:0] $end
   $var wire 8 P coeffs[4] [7:0] $end
   $var wire 8 Q coeffs[5] [7:0] $end
   $var wire 8 R coeffs[6] [7:0] $end
   $var wire 8 S coeffs[7] [7:0] $end
   $var wire 8 T coeffs[8] [7:0] $end
   $var wire 8 U coeffs[9] [7:0] $end
   $var wire 8 V coeffs[10] [7:0] $end
   $var wire 8 W coeffs[11] [7:0] $end
   $var wire 8 X coeffs[12] [7:0] $end
   $var wire 8 Y coeffs[13] [7:0] $end
   $var wire 8 Z coeffs[14] [7:0] $end
   $var wire 8 [ coeffs[15] [7:0] $end
   $var wire 8 \ coeffs[16] [7:0] $end
   $var wire 8 ] coeffs[17] [7:0] $end
   $var wire 8 ^ coeffs[18] [7:0] $end
   $var wire 8 _ coeffs[19] [7:0] $end
   $var wire 8 ` coeffs[20] [7:0] $end
   $var wire 8 a coeffs[21] [7:0] $end
   $var wire 8 b coeffs[22] [7:0] $end
   $var wire 8 c coeffs[23] [7:0] $end
   $var wire 8 d coeffs[24] [7:0] $end
   $var wire 8 e coeffs[25] [7:0] $end
   $var wire 8 f coeffs[26] [7:0] $end
   $var wire 8 g coeffs[27] [7:0] $end
   $var wire 8 h coeffs[28] [7:0] $end
   $var wire 8 i coeffs[29] [7:0] $end
   $var wire 8 j coeffs[30] [7:0] $end
   $var wire 8 k coeffs[31] [7:0] $end
   $var wire 8 # FIR[0] [7:0] $end
   $var wire 8 $ FIR[1] [7:0] $end
   $var wire 8 % FIR[2] [7:0] $end
   $var wire 8 & FIR[3] [7:0] $end
   $var wire 8 ' FIR[4] [7:0] $end
   $var wire 8 ( FIR[5] [7:0] $end
   $var wire 8 ) FIR[6] [7:0] $end
   $var wire 8 * FIR[7] [7:0] $end
   $var wire 8 + FIR[8] [7:0] $end
   $var wire 8 , FIR[9] [7:0] $end
   $var wire 8 - FIR[10] [7:0] $end
   $var wire 8 . FIR[11] [7:0] $end
   $var wire 8 / FIR[12] [7:0] $end
   $var wire 8 0 FIR[13] [7:0] $end
   $var wire 8 1 FIR[14] [7:0] $end
   $var wire 8 2 FIR[15] [7:0] $end
   $var wire 8 3 FIR[16] [7:0] $end
   $var wire 8 4 FIR[17] [7:0] $end
   $var wire 8 5 FIR[18] [7:0] $end
   $var wire 8 6 FIR[19] [7:0] $end
   $var wire 8 7 FIR[20] [7:0] $end
   $var wire 8 8 FIR[21] [7:0] $end
   $var wire 8 9 FIR[22] [7:0] $end
   $var wire 8 : FIR[23] [7:0] $end
   $var wire 8 ; FIR[24] [7:0] $end
   $var wire 8 < FIR[25] [7:0] $end
   $var wire 8 = FIR[26] [7:0] $end
   $var wire 8 > FIR[27] [7:0] $end
   $var wire 8 ? FIR[28] [7:0] $end
   $var wire 8 @ FIR[29] [7:0] $end
   $var wire 8 A FIR[30] [7:0] $end
   $var wire 8 B FIR[31] [7:0] $end
   $var wire 17 C acc [16:0] $end
   $var wire 32 l j [31:0] $end
   $var wire 32 D i [31:0] $end
  $upscope $end
 $upscope $end
$enddefinitions $end


#0
b01111000 #
b10111100 $
b10110110 %
b11100100 &
b10110111 '
b01010011 (
b00100001 )
b11100001 *
b11000101 +
b10000010 ,
b01100010 -
b00110101 .
b00010010 /
b01010110 0
b11111101 1
b11110100 2
b00111011 3
b01011000 4
b10110010 5
b01011100 6
b00011110 7
b10011110 8
b10011110 9
b11101110 :
b00010000 ;
b01110110 <
b01100011 =
b11000000 >
b00011101 ?
b00100010 @
b00000110 A
b10000001 B
b01001011011110001 C
b11000100010101001100001001111000 D
1E
0F
b00000010 G
b01001011011110001 H
b00000000000000000000000000100000 I
b00000000000000000000000000001000 J
b00000000000000000000000000010001 K
b00000011 L
b00000010 M
b00000001 N
b00000000 O
b00000000 P
b00000000 Q
b00000000 R
b00000000 S
b00000000 T
b00000000 U
b00000100 V
b00001100 W
b00010101 X
b00011110 Y
b00100101 Z
b00101001 [
b00101001 \
b00100101 ]
b00011110 ^
b00010101 _
b00001100 `
b00000100 a
b00000000 b
b00000000 c
b00000000 d
b00000000 e
b00000000 f
b00000000 g
b00000000 h
b00000001 i
b00000010 j
b00000011 k
b00000000000000000000000000100000 l
#1
0E
#2
b00000000 #
b00000000 $
b00000000 %
b00000000 &
b00000000 '
b00000000 (
b00000000 )
b00000000 *
b00000000 +
b00000000 ,
b00000000 -
b00000000 .
b00000000 /
b00000000 0
b00000000 1
b00000000 2
b00000000 3
b00000000 4
b00000000 5
b00000000 6
b00000000 7
b00000000 8
b00000000 9
b00000000 :
b00000000 ;
b00000000 <
b00000000 =
b00000000 >
b00000000 ?
b00000000 @
b00000000 A
b00000000 B
b00000000000000000 C
b00000000000000000000000000100000 D
1E
1F
b00000000000000000 H
#3
0E
#4
1E
#5
0E
#6
b00000010 #
b00000000000000110 C
b00000000000000000000000000000000 D
1E
0F
b00000000000000110 H
#7
0E
#8
b00000010 $
b00000000000001010 C
1E
b10000000 G
b00000000000001010 H
#9
0E
#10
b10000000 #
b00000010 %
b00000000110000110 C
1E
b11111000 G
b00000000110000110 H
#11
0E
#12
b11111000 #
b10000000 $
b00000010 &
b00000001111101010 C
1E
b11001010 G
b00000001111101010 H
#13
0E
#14
b11001010 #
b11111000 $
b10000000 %
b00000010 '
b00000010011001110 C
1E
b00110101 G
b00000010011001110 H
#15
0E
#16
b00110101 #
b11001010 $
b11111000 %
b10000000 &
b00000010 (
b00000001100101011 C
1E
b00000111 G
b00000001100101011 H
#17
0E
#18
b00000111 #
b00110101 $
b11001010 %
b11111000 &
b10000000 '
b00000010 )
b00000000101001001 C
1E
b01111111 G
b00000000101001001 H
#19
0E
#20
b01111111 #
b00000111 $
b00110101 %
b11001010 &
b11111000 '
b10000000 (
b00000010 *
b00000000111000000 C
1E
b11111000 G
b00000000111000000 H
#21
0E
#22
b11111000 #
b01111111 $
b00000111 %
b00110101 &
b11001010 '
b11111000 (
b10000000 )
b00000010 +
b00000001111101101 C
1E
b11001010 G
b00000001111101101 H
#23
0E
#24
b11001010 #
b11111000 $
b01111111 %
b00000111 &
b00110101 '
b11001010 (
b11111000 )
b10000000 *
b00000010 ,
b00000010011001101 C
1E
b00110101 G
b00000010011001101 H
#25
0E
#26
b00110101 #
b11001010 $
b11111000 %
b01111111 &
b00000111 '
b00110101 (
b11001010 )
b11111000 *
b10000000 +
b00000010 -
b00000001100110011 C
1E
b00000111 G
b00000001100110011 H
#27
0E
#28
b00000111 #
b00110101 $
b11001010 %
b11111000 &
b01111111 '
b00000111 (
b00110101 )
b11001010 *
b11111000 +
b10000000 ,
b00000010 .
b00000000101101001 C
1E
b01111111 G
b00000000101101001 H
#29
0E
#30
b01111111 #
b00000111 $
b00110101 %
b11001010 &
b11111000 '
b01111111 (
b00000111 )
b00110101 *
b11001010 +
b11111000 ,
b10000000 -
b00000010 /
b00000010000000010 C
1E
b11111000 G
b00000010000000010 H
#31
0E
#32
b11111000 #
b01111111 $
b00000111 %
b00110101 &
b11001010 '
b11111000 (
b01111111 )
b00000111 *
b00110101 +
b11001010 ,
b11111000 -
b10000000 .
b00000010 0
b00000111000110011 C
1E
b11001010 G
b00000111000110011 H
#33
0E
#34
b11001010 #
b11111000 $
b01111111 %
b00000111 &
b00110101 '
b11001010 (
b11111000 )
b01111111 *
b00000111 +
b00110101 ,
b11001010 -
b11111000 .
b10000000 /
b00000010 1
b00001111010011011 C
1E
b00110101 G
b00001111010011011 H
#35
0E
#36
b00110101 #
b11001010 $
b11111000 %
b01111111 &
b00000111 '
b00110101 (
b11001010 )
b11111000 *
b01111111 +
b00000111 ,
b00110101 -
b11001010 .
b11111000 /
b10000000 0
b00000010 2
b00011000101101011 C
1E
b00000111 G
b00011000101101011 H
#37
0E
#38
b00000111 #
b00110101 $
b11001010 %
b11111000 &
b01111111 '
b00000111 (
b00110101 )
b11001010 *
b11111000 +
b01111111 ,
b00000111 -
b00110101 .
b11001010 /
b11111000 0
b10000000 1
b00000010 3
b00100010010100111 C
1E
b01111111 G
b00100010010100111 H
#39
0E
#40
b01111111 #
b00000111 $
b00110101 %
b11001010 &
b11111000 '
b01111111 (
b00000111 )
b00110101 *
b11001010 +
b11111000 ,
b01111111 -
b00000111 .
b00110101 /
b11001010 0
b11111000 1
b10000000 2
b00000010 4
b00101100100001001 C
1E
b11111000 G
b00101100100001001 H
#41
0E
#42
b11111000 #
b01111111 $
b00000111 %
b00110101 &
b11001010 '
b11111000 (
b01111111 )
b00000111 *
b00110101 +
b11001010 ,
b11111000 -
b01111111 .
b00000111 /
b00110101 0
b11001010 1
b11111000 2
b10000000 3
b00000010 5
b00110111001111010 C
1E
b11001010 G
b00110111001111010 H
#43
0E
#44
b11001010 #
b11111000 $
b01111111 %
b00000111 &
b00110101 '
b11001010 (
b11111000 )
b01111111 *
b00000111 +
b00110101 ,
b11001010 -
b11111000 .
b01111111 /
b00000111 0
b00110101 1
b11001010 2
b11111000 3
b10000000 4
b00000010 6
b01000000101110011 C
1E
b00110101 G
b01000000101110011 H
#45
0E
#46
b00110101 #
b11001010 $
b11111000 %
b01111111 &
b00000111 '
b00110101 (
b11001010 )
b11111000 *
b01111111 +
b00000111 ,
b00110101 -
b11001010 .
b11111000 /
b01111111 0
b00000111 1
b00110101 2
b11001010 3
b11111000 4
b10000000 5
b00000010 7
b01000110110100101 C
1E
b00000111 G
b01000110110100101 H
#47
0E
#48
b00000111 #
b00110101 $
b11001010 %
b11111000 &
b01111111 '
b00000111 (
b00110101 )
b11001010 *
b11111000 +
b01111111 ,
b00000111 -
b00110101 .
b11001010 /
b11111000 0
b01111111 1
b00000111 2
b00110101 3
b11001010 4
b11111000 5
b10000000 6
b00000010 8
b01001001001011100 C
1E
b01111111 G
b01001001001011100 H
#49
0E
#50
b01111111 #
b00000111 $
b00110101 %
b11001010 &
b11111000 '
b01111111 (
b00000111 )
b00110101 *
b11001010 +
b11111000 ,
b01111111 -
b00000111 .
b00110101 /
b11001010 0
b11111000 1
b01111111 2
b00000111 3
b00110101 4
b11001010 5
b11111000 6
b10000000 7
b00000010 9
b01001001100011000 C
1E
b11111000 G
b01001001100011000 H
#51
0E
#52
b11111000 #
b01111111 $
b00000111 %
b00110101 &
b11001010 '
b11111000 (
b01111111 )
b00000111 *
b00110101 +
b11001010 ,
b11111000 -
b01111111 .
b00000111 /
b00110101 0
b11001010 1
b11111000 2
b01111111 3
b00000111 4
b00110101 5
b11001010 6
b11111000 7
b10000000 8
b00000010 :
b01001001100110110 C
1E
b11001010 G
b01001001100110110 H
#53
0E
#54
b11001010 #
b11111000 $
b01111111 %
b00000111 &
b00110101 '
b11001010 (
b11111000 )
b01111111 *
b00000111 +
b00110101 ,
b11001010 -
b11111000 .
b01111111 /
b00000111 0
b00110101 1
b11001010 2
b11111000 3
b01111111 4
b00000111 5
b00110101 6
b11001010 7
b11111000 8
b10000000 9
b00000010 ;
b01001001101101011 C
1E
b00110101 G
b01001001101101011 H
#55
0E
#56
b00110101 #
b11001010 $
b11111000 %
b01111111 &
b00000111 '
b00110101 (
b11001010 )
b11111000 *
b01111111 +
b00000111 ,
b00110101 -
b11001010 .
b11111000 /
b01111111 0
b00000111 1
b00110101 2
b11001010 3
b11111000 4
b01111111 5
b00000111 6
b00110101 7
b11001010 8
b11111000 9
b10000000 :
b00000010 <
b01001001101111100 C
1E
b00000111 G
b01001001101111100 H
#57
0E
#58
b00000111 #
b00110101 $
b11001010 %
b11111000 &
b01111111 '
b00000111 (
b00110101 )
b11001010 *
b11111000 +
b01111111 ,
b00000111 -
b00110101 .
b11001010 /
b11111000 0
b01111111 1
b00000111 2
b00110101 3
b11001010 4
b11111000 5
b01111111 6
b00000111 7
b00110101 8
b11001010 9
b11111000 :
b10000000 ;
b00000010 =
b01001001101001111 C
1E
b01111111 G
b01001001101001111 H
#59
0E
#60
b01111111 #
b00000111 $
b00110101 %
b11001010 &
b11111000 '
b01111111 (
b00000111 )
b00110101 *
b11001010 +
b11111000 ,
b01111111 -
b00000111 .
b00110101 /
b11001010 0
b11111000 1
b01111111 2
b00000111 3
b00110101 4
b11001010 5
b11111000 6
b01111111 7
b00000111 8
b00110101 9
b11001010 :
b11111000 ;
b10000000 <
b00000010 >
b01001001100100000 C
1E
b11111000 G
b01001001100100000 H
#61
0E
#62
b11111000 #
b01111111 $
b00000111 %
b00110101 &
b11001010 '
b11111000 (
b01111111 )
b00000111 *
b00110101 +
b11001010 ,
b11111000 -
b01111111 .
b00000111 /
b00110101 0
b11001010 1
b11111000 2
b01111111 3
b00000111 4
b00110101 5
b11001010 6
b11111000 7
b01111111 8
b00000111 9
b00110101 :
b11001010 ;
b11111000 <
b10000000 =
b00000010 ?
b01001001100110010 C
1E
b11001010 G
b01001001100110010 H
#63
0E
#64
b11001010 #
b11111000 $
b01111111 %
b00000111 &
b00110101 '
b11001010 (
b11111000 )
b01111111 *
b00000111 +
b00110101 ,
b11001010 -
b11111000 .
b01111111 /
b00000111 0
b00110101 1
b11001010 2
b11111000 3
b01111111 4
b00000111 5
b00110101 6
b11001010 7
b11111000 8
b01111111 9
b00000111 :
b00110101 ;
b11001010 <
b11111000 =
b10000000 >
b00000010 @
b01001001101101101 C
1E
b00110101 G
b01001001101101101 H
#65
0E
#66
b00110101 #
b11001010 $
b11111000 %
b01111111 &
b00000111 '
b00110101 (
b11001010 )
b11111000 *
b01111111 +
b00000111 ,
b00110101 -
b11001010 .
b11111000 /
b01111111 0
b00000111 1
b00110101 2
b11001010 3
b11111000 4
b01111111 5
b00000111 6
b00110101 7
b11001010 8
b11111000 9
b01111111 :
b00000111 ;
b00110101 <
b11001010 =
b11111000 >
b10000000 ?
b00000010 A
b01001001110000010 C
1E
b00000111 G
b01001001110000010 H
#67
0E
#68
b00000111 #
b00110101 $
b11001010 %
b11111000 &
b01111111 '
b00000111 (
b00110101 )
b11001010 *
b11111000 +
b01111111 ,
b00000111 -
b00110101 .
b11001010 /
b11111000 0
b01111111 1
b00000111 2
b00110101 3
b11001010 4
b11111000 5
b01111111 6
b00000111 7
b00110101 8
b11001010 9
b11111000 :
b01111111 ;
b00000111 <
b00110101 =
b11001010 >
b11111000 ?
b10000000 @
b00000010 B
b01001001111011001 C
1E
b01111111 G
b01001001111011001 H
#69
0E
#70
b01111111 #
b00000111 $
b00110101 %
b11001010 &
b11111000 '
b01111111 (
b00000111 )
b00110101 *
b11001010 +
b11111000 ,
b01111111 -
b00000111 .
b00110101 /
b11001010 0
b11111000 1
b01111111 2
b00000111 3
b00110101 4
b11001010 5
b11111000 6
b01111111 7
b00000111 8
b00110101 9
b11001010 :
b11111000 ;
b01111111 <
b00000111 =
b00110101 >
b11001010 ?
b11111000 @
b10000000 A
b01001010100011110 C
1E
b11111000 G
b01001010100011110 H
#71
0E
#72
b11111000 #
b01111111 $
b00000111 %
b00110101 &
b11001010 '
b11111000 (
b01111111 )
b00000111 *
b00110101 +
b11001010 ,
b11111000 -
b01111111 .
b00000111 /
b00110101 0
b11001010 1
b11111000 2
b01111111 3
b00000111 4
b00110101 5
b11001010 6
b11111000 7
b01111111 8
b00000111 9
b00110101 :
b11001010 ;
b11111000 <
b01111111 =
b00000111 >
b00110101 ?
b11001010 @
b11111000 A
b10000000 B
b01001011101101100 C
1E
b11001010 G
b01001011101101100 H
#73
0E
#74
b11001010 #
b11111000 $
b01111111 %
b00000111 &
b00110101 '
b11001010 (
b11111000 )
b01111111 *
b00000111 +
b00110101 ,
b11001010 -
b11111000 .
b01111111 /
b00000111 0
b00110101 1
b11001010 2
b11111000 3
b01111111 4
b00000111 5
b00110101 6
b11001010 7
b11111000 8
b01111111 9
b00000111 :
b00110101 ;
b11001010 <
b11111000 =
b01111111 >
b00000111 ?
b00110101 @
b11001010 A
b11111000 B
b01001100000011100 C
1E
b00110101 G
b01001100000011100 H
#75
0E
#76
b00110101 #
b11001010 $
b11111000 %
b01111111 &
b00000111 '
b00110101 (
b11001010 )
b11111000 *
b01111111 +
b00000111 ,
b00110101 -
b11001010 .
b11111000 /
b01111111 0
b00000111 1
b00110101 2
b11001010 3
b11111000 4
b01111111 5
b00000111 6
b00110101 7
b11001010 8
b11111000 9
b01111111 :
b00000111 ;
b00110101 <
b11001010 =
b11111000 >
b01111111 ?
b00000111 @
b00110101 A
b11001010 B
b01001011001001011 C
1E
b00000111 G
b01001011001001011 H
#77
0E
#78
b00000111 #
b00110101 $
b11001010 %
b11111000 &
b01111111 '
b00000111 (
b00110101 )
b11001010 *
b11111000 +
b01111111 ,
b00000111 -
b00110101 .
b11001010 /
b11111000 0
b01111111 1
b00000111 2
b00110101 3
b11001010 4
b11111000 5
b01111111 6
b00000111 7
b00110101 8
b11001010 9
b11111000 :
b01111111 ;
b00000111 <
b00110101 =
b11001010 >
b11111000 ?
b01111111 @
b00000111 A
b00110101 B
b01001010001111011 C
1E
b01111111 G
b01001010001111011 H
#79
0E
#80
b01111111 #
b00000111 $
b00110101 %
b11001010 &
b11111000 '
b01111111 (
b00000111 )
b00110101 *
b11001010 +
b11111000 ,
b01111111 -
b00000111 .
b00110101 /
b11001010 0
b11111000 1
b01111111 2
b00000111 3
b00110101 4
b11001010 5
b11111000 6
b01111111 7
b00000111 8
b00110101 9
b11001010 :
b11111000 ;
b01111111 <
b00000111 =
b00110101 >
b11001010 ?
b11111000 @
b01111111 A
b00000111 B
b01001010100101011 C
1E
b11111000 G
b01001010100101011 H
#81
0E
#82
b11111000 #
b01111111 $
b00000111 %
b00110101 &
b11001010 '
b11111000 (
b01111111 )
b00000111 *
b00110101 +
b11001010 ,
b11111000 -
b01111111 .
b00000111 /
b00110101 0
b11001010 1
b11111000 2
b01111111 3
b00000111 4
b00110101 5
b11001010 6
b11111000 7
b01111111 8
b00000111 9
b00110101 :
b11001010 ;
b11111000 <
b01111111 =
b00000111 >
b00110101 ?
b11001010 @
b11111000 A
b01111111 B
b01001011101101001 C
1E
b11001010 G
b01001011101101001 H
#83
0E
#84
b11001010 #
b11111000 $
b01111111 %
b00000111 &
b00110101 '
b11001010 (
b11111000 )
b01111111 *
b00000111 +
b00110101 ,
b11001010 -
b11111000 .
b01111111 /
b00000111 0
b00110101 1
b11001010 2
b11111000 3
b01111111 4
b00000111 5
b00110101 6
b11001010 7
b11111000 8
b01111111 9
b00000111 :
b00110101 ;
b11001010 <
b11111000 =
b01111111 >
b00000111 ?
b00110101 @
b11001010 A
b11111000 B
b01001100000011100 C
1E
b00110101 G
b01001100000011100 H
#85
0E
#86
b00110101 #
b11001010 $
b11111000 %
b01111111 &
b00000111 '
b00110101 (
b11001010 )
b11111000 *
b01111111 +
b00000111 ,
b00110101 -
b11001010 .
b11111000 /
b01111111 0
b00000111 1
b00110101 2
b11001010 3
b11111000 4
b01111111 5
b00000111 6
b00110101 7
b11001010 8
b11111000 9
b01111111 :
b00000111 ;
b00110101 <
b11001010 =
b11111000 >
b01111111 ?
b00000111 @
b00110101 A
b11001010 B
b01001011001001011 C
1E
b00000111 G
b01001011001001011 H
#87
0E
#88
b00000111 #
b00110101 $
b11001010 %
b11111000 &
b01111111 '
b00000111 (
b00110101 )
b11001010 *
b11111000 +
b01111111 ,
b00000111 -
b00110101 .
b11001010 /
b11111000 0
b01111111 1
b00000111 2
b00110101 3
b11001010 4
b11111000 5
b01111111 6
b00000111 7
b00110101 8
b11001010 9
b11111000 :
b01111111 ;
b00000111 <
b00110101 =
b11001010 >
b11111000 ?
b01111111 @
b00000111 A
b00110101 B
b01001010001111011 C
1E
b01111111 G
b01001010001111011 H
#89
0E
#90
b01111111 #
b00000111 $
b00110101 %
b11001010 &
b11111000 '
b01111111 (
b00000111 )
b00110101 *
b11001010 +
b11111000 ,
b01111111 -
b00000111 .
b00110101 /
b11001010 0
b11111000 1
b01111111 2
b00000111 3
b00110101 4
b11001010 5
b11111000 6
b01111111 7
b00000111 8
b00110101 9
b11001010 :
b11111000 ;
b01111111 <
b00000111 =
b00110101 >
b11001010 ?
b11111000 @
b01111111 A
b00000111 B
b01001010100101011 C
1E
b11111000 G
b01001010100101011 H
#91
0E
#92
b11111000 #
b01111111 $
b00000111 %
b00110101 &
b11001010 '
b11111000 (
b01111111 )
b00000111 *
b00110101 +
b11001010 ,
b11111000 -
b01111111 .
b00000111 /
b00110101 0
b11001010 1
b11111000 2
b01111111 3
b00000111 4
b00110101 5
b11001010 6
b11111000 7
b01111111 8
b00000111 9
b00110101 :
b11001010 ;
b11111000 <
b01111111 =
b00000111 >
b00110101 ?
b11001010 @
b11111000 A
b01111111 B
b01001011101101001 C
1E
b11001010 G
b01001011101101001 H
#93
0E
#94
b11001010 #
b11111000 $
b01111111 %
b00000111 &
b00110101 '
b11001010 (
b11111000 )
b01111111 *
b00000111 +
b00110101 ,
b11001010 -
b11111000 .
b01111111 /
b00000111 0
b00110101 1
b11001010 2
b11111000 3
b01111111 4
b00000111 5
b00110101 6
b11001010 7
b11111000 8
b01111111 9
b00000111 :
b00110101 ;
b11001010 <
b11111000 =
b01111111 >
b00000111 ?
b00110101 @
b11001010 A
b11111000 B
b01001100000011100 C
1E
b00110101 G
b01001100000011100 H
#95
0E
#96
b00110101 #
b11001010 $
b11111000 %
b01111111 &
b00000111 '
b00110101 (
b11001010 )
b11111000 *
b01111111 +
b00000111 ,
b00110101 -
b11001010 .
b11111000 /
b01111111 0
b00000111 1
b00110101 2
b11001010 3
b11111000 4
b01111111 5
b00000111 6
b00110101 7
b11001010 8
b11111000 9
b01111111 :
b00000111 ;
b00110101 <
b11001010 =
b11111000 >
b01111111 ?
b00000111 @
b00110101 A
b11001010 B
b01001011001001011 C
1E
b00000111 G
b01001011001001011 H
#97
0E
#98
b00000111 #
b00110101 $
b11001010 %
b11111000 &
b01111111 '
b00000111 (
b00110101 )
b11001010 *
b11111000 +
b01111111 ,
b00000111 -
b00110101 .
b11001010 /
b11111000 0
b01111111 1
b00000111 2
b00110101 3
b11001010 4
b11111000 5
b01111111 6
b00000111 7
b00110101 8
b11001010 9
b11111000 :
b01111111 ;
b00000111 <
b00110101 =
b11001010 >
b11111000 ?
b01111111 @
b00000111 A
b00110101 B
b01001010001111011 C
1E
b01111111 G
b01001010001111011 H
#99
0E
#100
b01111111 #
b00000111 $
b00110101 %
b11001010 &
b11111000 '
b01111111 (
b00000111 )
b00110101 *
b11001010 +
b11111000 ,
b01111111 -
b00000111 .
b00110101 /
b11001010 0
b11111000 1
b01111111 2
b00000111 3
b00110101 4
b11001010 5
b11111000 6
b01111111 7
b00000111 8
b00110101 9
b11001010 :
b11111000 ;
b01111111 <
b00000111 =
b00110101 >
b11001010 ?
b11111000 @
b01111111 A
b00000111 B
b01001010100101011 C
1E
b11111000 G
b01001010100101011 H
#101
0E
#102
b11111000 #
b01111111 $
b00000111 %
b00110101 &
b11001010 '
b11111000 (
b01111111 )
b00000111 *
b00110101 +
b11001010 ,
b11111000 -
b01111111 .
b00000111 /
b00110101 0
b11001010 1
b11111000 2
b01111111 3
b00000111 4
b00110101 5
b11001010 6
b11111000 7
b01111111 8
b00000111 9
b00110101 :
b11001010 ;
b11111000 <
b01111111 =
b00000111 >
b00110101 ?
b11001010 @
b11111000 A
b01111111 B
b01001011101101001 C
1E
b11001010 G
b01001011101101001 H
#103
0E
#104
b11001010 #
b11111000 $
b01111111 %
b00000111 &
b00110101 '
b11001010 (
b11111000 )
b01111111 *
b00000111 +
b00110101 ,
b11001010 -
b11111000 .
b01111111 /
b00000111 0
b00110101 1
b11001010 2
b11111000 3
b01111111 4
b00000111 5
b00110101 6
b11001010 7
b11111000 8
b01111111 9
b00000111 :
b00110101 ;
b11001010 <
b11111000 =
b01111111 >
b00000111 ?
b00110101 @
b11001010 A
b11111000 B
b01001100000011100 C
1E
b00110101 G
b01001100000011100 H
#105
0E
#106
b00110101 #
b11001010 $
b11111000 %
b01111111 &
b00000111 '
b00110101 (
b11001010 )
b11111000 *
b01111111 +
b00000111 ,
b00110101 -
b11001010 .
b11111000 /
b01111111 0
b00000111 1
b00110101 2
b11001010 3
b11111000 4
b01111111 5
b00000111 6
b00110101 7
b11001010 8
b11111000 9
b01111111 :
b00000111 ;
b00110101 <
b11001010 =
b11111000 >
b01111111 ?
b00000111 @
b00110101 A
b11001010 B
b01001011001001011 C
1E
b00000111 G
b01001011001001011 H
#107
0E
#108
b00000111 #
b00110101 $
b11001010 %
b11111000 &
b01111111 '
b00000111 (
b00110101 )
b11001010 *
b11111000 +
b01111111 ,
b00000111 -
b00110101 .
b11001010 /
b11111000 0
b01111111 1
b00000111 2
b00110101 3
b11001010 4
b11111000 5
b01111111 6
b00000111 7
b00110101 8
b11001010 9
b11111000 :
b01111111 ;
b00000111 <
b00110101 =
b11001010 >
b11111000 ?
b01111111 @
b00000111 A
b00110101 B
b01001010001111011 C
1E
b01111111 G
b01001010001111011 H
#109
0E
#110
b01111111 #
b00000111 $
b00110101 %
b11001010 &
b11111000 '
b01111111 (
b00000111 )
b00110101 *
b11001010 +
b11111000 ,
b01111111 -
b00000111 .
b00110101 /
b11001010 0
b11111000 1
b01111111 2
b00000111 3
b00110101 4
b11001010 5
b11111000 6
b01111111 7
b00000111 8
b00110101 9
b11001010 :
b11111000 ;
b01111111 <
b00000111 =
b00110101 >
b11001010 ?
b11111000 @
b01111111 A
b00000111 B
b01001010100101011 C
1E
b11111000 G
b01001010100101011 H
#111
0E
#112
b11111000 #
b01111111 $
b00000111 %
b00110101 &
b11001010 '
b11111000 (
b01111111 )
b00000111 *
b00110101 +
b11001010 ,
b11111000 -
b01111111 .
b00000111 /
b00110101 0
b11001010 1
b11111000 2
b01111111 3
b00000111 4
b00110101 5
b11001010 6
b11111000 7
b01111111 8
b00000111 9
b00110101 :
b11001010 ;
b11111000 <
b01111111 =
b00000111 >
b00110101 ?
b11001010 @
b11111000 A
b01111111 B
b01001011101101001 C
1E
b11001010 G
b01001011101101001 H
#113
0E
#114
b11001010 #
b11111000 $
b01111111 %
b00000111 &
b00110101 '
b11001010 (
b11111000 )
b01111111 *
b00000111 +
b00110101 ,
b11001010 -
b11111000 .
b01111111 /
b00000111 0
b00110101 1
b11001010 2
b11111000 3
b01111111 4
b00000111 5
b00110101 6
b11001010 7
b11111000 8
b01111111 9
b00000111 :
b00110101 ;
b11001010 <
b11111000 =
b01111111 >
b00000111 ?
b00110101 @
b11001010 A
b11111000 B
b01001100000011100 C
1E
b00110101 G
b01001100000011100 H
#115
0E
#116
b00110101 #
b11001010 $
b11111000 %
b01111111 &
b00000111 '
b00110101 (
b11001010 )
b11111000 *
b01111111 +
b00000111 ,
b00110101 -
b11001010 .
b11111000 /
b01111111 0
b00000111 1
b00110101 2
b11001010 3
b11111000 4
b01111111 5
b00000111 6
b00110101 7
b11001010 8
b11111000 9
b01111111 :
b00000111 ;
b00110101 <
b11001010 =
b11111000 >
b01111111 ?
b00000111 @
b00110101 A
b11001010 B
b01001011001001011 C
1E
b00000111 G
b01001011001001011 H
#117
0E
